pytest_dryrun/__init__.py
pytest_dryrun/py.typed
pytest_dryrun/pytest_dryrun.py
pytest_dryrun-1.0.1.dist-info/LICENSE.md
pytest_dryrun-1.0.1.dist-info/METADATA
pytest_dryrun-1.0.1.dist-info/WHEEL
pytest_dryrun-1.0.1.dist-info/entry_points.txt
pytest_dryrun-1.0.1.dist-info/RECORD
