Metadata-Version: 2.3
Name: pytest-dryrun
Version: 1.0.1
Summary: A Pytest plugin to ignore tests during collection without reporting them in the test summary.
License: MIT
Author: Maddy Guthridge
Author-email: hello@maddyguthridge.com
Requires-Python: >3.9
Classifier: Programming Language :: Python :: 3
Classifier: Intended Audience :: Education
Classifier: License :: OSI Approved :: MIT License
Classifier: Operating System :: OS Independent
Classifier: Development Status :: 5 - Production/Stable
Classifier: Environment :: Plugins
Classifier: Framework :: Pytest
Classifier: Topic :: Education :: Testing
Classifier: Typing :: Typed
Requires-Dist: pytest (>=7.40,<9)
Project-URL: Bug Tracker, https://github.com/COMP1010UNSW/pytest-dryrun/issues
Project-URL: Documentation, https://github.com/COMP1010UNSW/pytest-dryrun#readme
Project-URL: Repository, https://github.com/COMP1010UNSW/pytest-dryrun
